AIMaker/VERSION
AIMaker/__init__.py
AIMaker/update_result.py
AIMaker-1.4.4.dist-info/LICENSE
AIMaker-1.4.4.dist-info/METADATA
AIMaker-1.4.4.dist-info/WHEEL
AIMaker-1.4.4.dist-info/top_level.txt
AIMaker-1.4.4.dist-info/RECORD
