Metadata-Version: 2.1
Name: AIMaker
Version: 1.4.4
Summary: Return training result to api server
Author: chris
Author-email: chris5_lin@asus.com
License: MIT
License-File: LICENSE
Requires-Dist: urllib3 <2
